{
    "tabsBasicCode" : "<nz-tabset>\r\n    <nz-tab nzTitle=\"Tab 1\">\r\n        Content of Tab Pane 1\r\n    <\/nz-tab>\r\n    <nz-tab nzTitle=\"Tab 2\">\r\n        Content of Tab Pane 2\r\n    <\/nz-tab>\r\n    <nz-tab nzTitle=\"Tab 3\">\r\n        Content of Tab Pane 3\r\n    <\/nz-tab>\r\n<\/nz-tabset>",
    "tabsDisabledCode" : "import { Component } from '@angular\/core';\r\n\r\n@Component({\r\n    selector: 'nz-demo-tabs-disabled',\r\n    template: `\r\n        <nz-tabset>\r\n            <nz-tab\r\n                *ngFor=\"let tab of tabs\"\r\n                [nzTitle]=\"tab.name\"\r\n                [nzDisabled]=\"tab.disabled\">\r\n                {{ tab.name }}\r\n            <\/nz-tab>\r\n        <\/nz-tabset>`\r\n})\r\nexport class NzDemoTabsDisabledComponent {\r\n    tabs = [\r\n        {\r\n            name    : 'Tab 1',\r\n            disabled: false\r\n        },\r\n        {\r\n            name    : 'Tab 2',\r\n            disabled: true\r\n        },\r\n        {\r\n            name    : 'Tab 3',\r\n            disabled: false\r\n        }\r\n    ];\r\n}",
    "tabsIconCode" : "import { Component } from '@angular\/core';\r\n\r\n@Component({\r\n    selector: 'nz-demo-tabs-icon',\r\n    template: `\r\n        <nz-tabset>\r\n            <nz-tab *ngFor=\"let tab of tabs\" [nzTitle]=\"titleTemplate\">\r\n                <ng-template #titleTemplate>\r\n                    <i nz-icon [nzType]=\"tab.icon\"><\/i>{{ tab.name }}\r\n                <\/ng-template>\r\n            {{ tab.name }}\r\n            <\/nz-tab>\r\n        <\/nz-tabset>`\r\n})\r\nexport class NzDemoTabsIconComponent {\r\n    tabs = [\r\n        {\r\n            active: true,\r\n            name  : 'Tab 1',\r\n            icon  : 'apple'\r\n        },\r\n        {\r\n            active: false,\r\n            name  : 'Tab 2',\r\n            icon  : 'android'\r\n        }\r\n    ];\r\n}",
    "tabsSlideCode" : "import { Component, OnInit } from '@angular\/core';\r\n\r\n@Component({\r\n    selector: 'nz-demo-tabs-slide',\r\n    template: `\r\n        <nz-radio-group [(ngModel)]=\"nzTabPosition\">\r\n            <label nz-radio-button [nzValue]=\"'top'\">Horizontal<\/label>\r\n            <label nz-radio-button [nzValue]=\"'left'\">Vertical<\/label>\r\n        <\/nz-radio-group>\r\n        <nz-input-number style=\"float:right;\" [nzMin]=\"0\" [nzMax]=\"10\" [(ngModel)]=\"selectedIndex\"><\/nz-input-number>\r\n        <nz-tabset\r\n            style=\"height:220px;\"\r\n            [nzTabPosition]=\"nzTabPosition\"\r\n            [(nzSelectedIndex)]=\"selectedIndex\"\r\n            (nzSelectChange)=\"log([$event])\">\r\n            <nz-tab\r\n                *ngFor=\"let tab of tabs\"\r\n                [nzTitle]=\"tab.name\"\r\n                (nzSelect)=\"log(['select',tab])\"\r\n                (nzClick)=\"log(['click',tab])\"\r\n                (nzDeselect)=\"log(['deselect',tab])\">\r\n                {{ tab.content }}\r\n            <\/nz-tab>\r\n        <\/nz-tabset>`\r\n})\r\nexport class NzDemoTabsSlideComponent implements OnInit {\r\n    tabs = [];\r\n    nzTabPosition = 'top';\r\n    selectedIndex = 0;\r\n\r\n    \/* tslint:disable-next-line:no-any *\/\r\n        log(args: any[]): void {\r\n        console.log(args);\r\n    }\r\n\r\n    ngOnInit(): void {\r\n        for (let i = 0; i < 11; i++) {\r\n            this.tabs.push({\r\n                name   : `Tab ${i}`,\r\n                content: `Content of tab ${i}`\r\n            });\r\n        }\r\n    }\r\n}",
    "tabsExtraContentCode" : "import { Component } from '@angular\/core';\r\n\r\n@Component({\r\n    selector: 'nz-demo-tabs-extra',\r\n    template: `\r\n        <nz-tabset [nzTabBarExtraContent]=\"extraTemplate\">\r\n            <nz-tab *ngFor=\"let tab of tabs\" [nzTitle]=\"'Tab' + tab \">\r\n                Content of tab {{ tab }}\r\n            <\/nz-tab>\r\n        <\/nz-tabset>\r\n        <ng-template #extraTemplate>\r\n            <button nz-button>Extra Action<\/button>\r\n        <\/ng-template>\r\n    `\r\n})\r\nexport class NzDemoTabsExtraComponent {\r\n    tabs = [ 1, 2, 3 ];\r\n}",
    "tabsSizeCode" : "import { Component } from '@angular\/core';\r\n\r\n@Component({\r\n    selector: 'nz-demo-tabs-size',\r\n    template: `\r\n        <nz-radio-group [(ngModel)]=\"size\">\r\n            <label nz-radio-button nzValue=\"small\"><span>Small<\/span><\/label>\r\n            <label nz-radio-button nzValue=\"default\"><span>Default<\/span><\/label>\r\n            <label nz-radio-button nzValue=\"large\"><span>Large<\/span><\/label>\r\n        <\/nz-radio-group>\r\n        <nz-tabset [nzSize]=\"size\">\r\n            <nz-tab *ngFor=\"let tab of tabs\" [nzTitle]=\"'Tab' + tab\">\r\n                Content of tab {{ tab }}\r\n            <\/nz-tab>\r\n        <\/nz-tabset>`\r\n})\r\nexport class NzDemoTabsSizeComponent {\r\n    size = 'small';\r\n    tabs = [ 1, 2, 3 ];\r\n}",
    "tabsPositionCode" : "import { Component } from '@angular\/core';\r\n\r\n@Component({\r\n    selector: 'nz-demo-tabs-position',\r\n    template: `\r\n        <div style=\"margin-bottom: 16px;\">\r\n            Tab position\uFF1A\r\n            <nz-select [(ngModel)]=\"position\" style=\"width: 80px;\">\r\n                <nz-option\r\n                    *ngFor=\"let option of options\"\r\n                    [nzLabel]=\"option.label\"\r\n                    [nzValue]=\"option.value\">\r\n                <\/nz-option>\r\n            <\/nz-select>\r\n        <\/div>\r\n        <nz-tabset [nzTabPosition]=\"position\" [nzType]=\"'line'\">\r\n            <nz-tab *ngFor=\"let tab of tabs\" [nzTitle]=\"'Tab'+ tab\">\r\n                Content of tab {{ tab }}\r\n            <\/nz-tab>\r\n        <\/nz-tabset>`\r\n})\r\nexport class NzDemoTabsPositionComponent {\r\n    position = 'top';\r\n    tabs = [ 1, 2, 3 ];\r\n    options = [\r\n        { value: 'top', label: 'top' },\r\n        { value: 'left', label: 'left' },\r\n        { value: 'right', label: 'right' },\r\n        { value: 'bottom', label: 'bottom' }\r\n    ];\r\n}",
    "tabsCardTypeCode" : "import { Component } from '@angular\/core';\r\n\r\n@Component({\r\n    selector: 'nz-demo-tabs-card',\r\n    template: `\r\n        <nz-tabset [nzTabPosition]=\"'top'\" [nzType]=\"'card'\">\r\n            <nz-tab *ngFor=\"let tab of tabs\" [nzTitle]=\"'Tab' + tab \">\r\n            Content of Tab Pane {{ tab }}\r\n            <\/nz-tab>\r\n        <\/nz-tabset>`\r\n})\r\nexport class NzDemoTabsCardComponent {\r\n    tabs = [ 1, 2, 3 ];\r\n}",
    "tabsCustomizedCode" : "import { Component } from '@angular\/core';\r\n\r\n@Component({\r\n    selector: 'nz-demo-tabs-custom-add-trigger',\r\n    template: `\r\n        <div class=\"m-b-15\">\r\n            <button nz-button (click)=\"newTab()\">ADD<\/button>\r\n        <\/div>\r\n        <nz-tabset [nzType]=\"'card'\" [nzSelectedIndex]=\"index\">\r\n            <nz-tab *ngFor=\"let tab of tabs\" [nzTitle]=\"titleTemplate\">\r\n                <ng-template #titleTemplate>\r\n                    <div>{{ tab }}<i nz-icon nzType=\"close\" class=\"ant-tabs-close-x\" (click)=\"closeTab(tab)\"><\/i><\/div>\r\n                <\/ng-template>\r\n                Content of {{ tab }}\r\n            <\/nz-tab>\r\n        <\/nz-tabset>`\r\n})\r\nexport class NzDemoTabsCustomAddTriggerComponent {\r\n    index = 0;\r\n    tabs = [ 'Tab 1', 'Tab 2' ];\r\n\r\n    closeTab(tab: string): void {\r\n        this.tabs.splice(this.tabs.indexOf(tab), 1);\r\n    }\r\n\r\n    newTab(): void {\r\n        this.tabs.push('New Tab');\r\n        this.index = this.tabs.length - 1;\r\n    }\r\n}",
    "tabsLazyCode": "\/* entryComponents: NzDemoTabContentLazyComponent,NzDemoTabContentEagerlyComponent *\/\r\nimport { Component, OnInit } from '@angular\/core';\r\n\r\n@Component({\r\n    selector: 'nz-demo-tabs-lazy',\r\n    template: `\r\n        <nz-tabset>\r\n        <nz-tab nzTitle=\"Tab Eagerly 1\">\r\n            <nz-demo-tab-content-eagerly><\/nz-demo-tab-content-eagerly>\r\n        <\/nz-tab>\r\n        <nz-tab nzTitle=\"Tab Eagerly 2\">\r\n            <nz-demo-tab-content-eagerly><\/nz-demo-tab-content-eagerly>\r\n        <\/nz-tab>\r\n        <nz-tab nzTitle=\"Tab Lazy 1\">\r\n            <ng-template nz-tab>\r\n                <nz-demo-tab-content-lazy><\/nz-demo-tab-content-lazy>\r\n            <\/ng-template>\r\n        <\/nz-tab>\r\n        <nz-tab nzTitle=\"Tab Lazy 2\">\r\n            <ng-template nz-tab>\r\n                <nz-demo-tab-content-lazy><\/nz-demo-tab-content-lazy>\r\n            <\/ng-template>\r\n        <\/nz-tab>\r\n        <\/nz-tabset>\r\n    `\r\n    })\r\nexport class NzDemoTabsLazyComponent {}\r\n\r\n@Component({\r\n    selector: 'nz-demo-tab-content-lazy',\r\n    template: `\r\n        lazy\r\n    `\r\n})\r\nexport class NzDemoTabContentLazyComponent implements OnInit {\r\n    ngOnInit(): void {\r\n        console.log(`I will init when tab active`);\r\n    }\r\n}\r\n\r\n@Component({\r\n    selector: 'nz-demo-tab-content-eagerly',\r\n    template: `\r\n        eagerly\r\n    `\r\n})\r\n\r\nexport class NzDemoTabContentEagerlyComponent implements OnInit {\r\n    ngOnInit(): void {\r\n        console.log(`I will init eagerly`);\r\n    }\r\n}",
    "tabsRouterCode": "import { Component } from '@angular\/core';\r\n\r\n@Component({\r\n    selector: 'nz-demo-tabs-link-router',\r\n    template: `\r\n        <nz-tabset nzLinkRouter>\r\n            <nz-tab>\r\n                <a nz-tab-link [routerLink]=\"['.']\" [queryParams]=\"{ tab: 'one' }\" queryParamsHandling=\"merge\">Default<\/a>\r\n                Default.\r\n            <\/nz-tab>\r\n            <nz-tab>\r\n                <a nz-tab-link [routerLink]=\"['.']\" [queryParams]=\"{ tab: 'two' }\" queryParamsHandling=\"merge\">Two<\/a>\r\n                Two.\r\n            <\/nz-tab>\r\n            <nz-tab>\r\n                <a nz-tab-link [routerLink]=\"['.']\" [queryParams]=\"{ tab: 'three' }\" queryParamsHandling=\"merge\">Three<\/a>\r\n                Three.\r\n            <\/nz-tab>\r\n            <nz-tab>\r\n                <a nz-tab-link [routerLink]=\"['.']\" [queryParams]=\"{ tab: 'four' }\" queryParamsHandling=\"merge\">Four<\/a>\r\n                Four.\r\n            <\/nz-tab>\r\n        <\/nz-tabset>\r\n    `\r\n})\r\nexport class NzDemoTabsLinkRouterComponent {}"
}